{
  "id": "b79a7bfb-b494-42d4-b415-a7e92f47911b",
  "uid": "impedit-nostrum-blanditiis",
  "type": "publication",
  "data": {
    "title": "e-enable enterprise initiatives",
    "content": [
      {
        "type": "heading1",
        "text": "Architect viral schemas",
        "spans": []
      },
      {
        "type": "paragraph",
        "text": "Nisi ut magna aliquip deserunt quis mollit sunt dolor pariatur ipsum enim do aute ullamco. Ut incididunt aliquip irure excepteur et do aliqua duis commodo est et excepteur. Proident deserunt nisi anim cillum adipisicing nulla ad mollit tempor nostrud laborum quis velit sit consequat.",
        "spans": []
      }
    ]
  }
}